{
  "id": "ordinary-time-32-c",
  "name": "ORDINARY TIME 32 [C]",
  "year": "C",
  "season": "ordinary",
  "seasonLabel": "Ordinary Time",
  "seasonOrder": 32,
  "dates": [
    {
      "date": "2037-11-08",
      "label": "Year C — Nov 08, 2037 (Sun)",
      "dayOfWeek": "Sun"
    },
    {
      "date": "2034-11-12",
      "label": "Year C — Nov 12, 2034 (Sun)",
      "dayOfWeek": "Sun"
    },
    {
      "date": "2028-11-12",
      "label": "Year C — Nov 12, 2028 (Sun)",
      "dayOfWeek": "Sun"
    }
  ],
  "lectionary": {
    "number": "156•C",
    "gospelTitle": "Perseverance Wins",
    "thematicTag": "End-Time Discourse 1/2"
  },
  "readings": [
    {
      "type": "first",
      "citation": "2 Mc 7:1-2, 9-14",
      "summary": "Seven brothers and their mother are tortured, but remain faithful."
    },
    {
      "type": "psalm",
      "citation": "Lord, when your glory appears, my joy will be full.",
      "summary": "",
      "antiphon": "Lord, when your glory appears, my joy will be full."
    },
    {
      "type": "second",
      "citation": "2 Thes 2:16 – 3:5",
      "summary": "The Lord will strengthen you in faith."
    },
    {
      "type": "gospel_verse",
      "citation": "Rev 1:5a, 6b",
      "summary": "Jesus Christ is the first born of the dead;\nto him be glory and power, forever and ever."
    },
    {
      "type": "gospel",
      "citation": "Lk 20:27-38 (Shorter - Lk 20:27, 34-38)",
      "summary": "The Sadducees try to put Jesus in conflict with Moses."
    }
  ],
  "antiphons": [
    {
      "type": "entrance",
      "option": 1,
      "citation": "Cf. Ps 88 (87):3",
      "text": "Let my prayer come into your presence.\nIncline your ear to my cry for help, O Lord."
    },
    {
      "type": "communion",
      "option": 1,
      "citation": "Cf. Ps 23 (22):1–2",
      "text": "The Lord is my shepherd; there is nothing I shall want.\nFresh and green are the pastures where he gives me repose,\nnear restful waters he leads me."
    },
    {
      "type": "communion",
      "option": 2,
      "citation": "Roman Missal — Cf. Lk 24:35",
      "text": "The disciples recognized the Lord Jesus\nin the breaking of bread."
    }
  ],
  "planningNotes": [
    "Black Catholic History Month",
    "Month of Remembrance"
  ],
  "musicPlans": [
    {
      "community": "Reflections",
      "communityId": "reflections",
      "date": "Year C — Nov 11, 2028 (Sat)",
      "presider": "NOT THIS YEAR",
      "gospelAcclamation": {
        "title": "Alleluia (Mass of Joy & Peace)",
        "composer": "Song Title"
      },
      "lordsPrayer": {
        "title": "Chanted Our Father (Snow)",
        "composer": "Jennings/Paregorius"
      },
      "fractionRite": {
        "title": "Lamb of God Setting"
      },
      "communionSongs": [
        {
          "title": "Psalm 23: Shepherd Me, O God",
          "composer": "Marty Haugen",
          "description": "OT32C"
        }
      ]
    },
    {
      "community": "Foundations",
      "communityId": "foundations",
      "date": "Year C — Nov 12, 2028 (Sun)",
      "presider": "NOT THIS YEAR",
      "penitentialAct": {
        "title": "Kyrie (Gift of God) • Adapted Version",
        "composer": "Marty Haugen • Arranged by David Locwood"
      },
      "gloria": {
        "title": "Glory to God (Mass of Joy & Peace)",
        "composer": "Alonso • Arr. by Houze OR Arr. by Lockwood"
      },
      "eucharisticAcclamations": {
        "massSettingName": "Mass of ?"
      },
      "lordsPrayer": {
        "title": "Chanted Our Father (Snow)",
        "composer": "Jennings • Paregorius"
      },
      "fractionRite": {
        "title": "Lamb of God (Mass of ???)"
      }
    },
    {
      "community": "Generations",
      "communityId": "generations",
      "date": "Year C — Nov 12, 2028 (Sun)",
      "presider": "NOT THIS YEAR",
      "penitentialAct": {
        "title": "Kyrie • Misa Del Mundo",
        "composer": "If needed. Talk to presider!"
      },
      "gloria": {
        "title": "Glory, Glory, Gloria!",
        "composer": "Tony Alonso • Arr. by Dan Houze"
      },
      "gospelAcclamation": {
        "title": "Setting from Mass of ???",
        "composer": "Song Title"
      },
      "eucharisticAcclamations": {
        "massSettingName": "Mass of ?"
      },
      "lordsPrayer": {
        "title": "(Echo) Our Father",
        "composer": "Jerome Andrews • Arranged by Dan Houze"
      },
      "fractionRite": {
        "title": "Lamb of God (Mass Setting?)"
      }
    },
    {
      "community": "Heritage",
      "communityId": "heritage",
      "date": "Year C — Nov 12, 2028 (Sun)",
      "presider": "NOT THIS YEAR",
      "penitentialAct": {
        "title": "Kyrie • Misa Del Mundo",
        "composer": "Only if needed. Talk to presider!"
      },
      "gloria": {
        "title": "Glory to God (Mass of Christ the Savior)",
        "composer": "Dan Schutte"
      },
      "eucharisticAcclamations": {
        "massSettingName": "Mass of Christ the Savior - Dan Schutte"
      },
      "lordsPrayer": {
        "title": "Echo Our Father",
        "composer": "Andrews, Arr. Bonilla • Lockwood • Fajardo"
      },
      "fractionRite": {
        "title": "Lamb of God (Mass of Christ the Savior)"
      }
    },
    {
      "community": "Elevations",
      "communityId": "elevations",
      "date": "Year C — Nov 12, 2028 (Sun)",
      "presider": "NOT THIS YEAR",
      "gospelAcclamation": {
        "title": "Setting from Mass of ???",
        "verse": "Song Title"
      },
      "eucharisticAcclamations": {
        "massSettingName": "Mass of Restoration • Joshua Blakesley"
      },
      "lordsPrayer": {
        "title": "Echo Our Father",
        "composer": "Andrews, Arr. Bonilla • Lockwood • Fajardo"
      },
      "fractionRite": {
        "title": "Lamb of God (Resoration)"
      }
    }
  ],
  "occasionResources": []
}