{
  "id": "ordinary-time-19-a",
  "name": "ORDINARY TIME 19 [A]",
  "year": "A",
  "season": "ordinary",
  "seasonLabel": "Ordinary Time",
  "seasonOrder": 19,
  "dates": [
    {
      "date": "2023-08-13",
      "label": "Year A — Aug 13, 2023 (Sun)",
      "dayOfWeek": "Sun"
    },
    {
      "date": "2035-08-12",
      "label": "Year A — Aug 12, 2035 (Sun)",
      "dayOfWeek": "Sun"
    },
    {
      "date": "2032-08-08",
      "label": "Year A — Aug 08, 2032 (Sun)",
      "dayOfWeek": "Sun"
    },
    {
      "date": "2029-08-12",
      "label": "Year A — Aug 12, 2029 (Sun)",
      "dayOfWeek": "Sun"
    },
    {
      "date": "2026-08-09",
      "label": "Year A — Aug 09, 2026 (Sun)",
      "dayOfWeek": "Sun"
    }
  ],
  "lectionary": {
    "number": "115•A",
    "gospelTitle": "Walks on Water",
    "thematicTag": "Loaves/Faith 2/2"
  },
  "readings": [
    {
      "type": "first",
      "citation": "1 Kings 19:9a, 11-13a",
      "summary": "The Lord passes by Elijah as a whisper."
    },
    {
      "type": "psalm",
      "citation": "Ps 85:9, 10, 11-12, 13-14. R. v.8\nLord, let us see your kindness, and grant us your salvation.",
      "summary": "",
      "antiphon": "Ps 85:9, 10, 11-12, 13-14. R. v.8\nLord, let us see your kindness, and grant us your salvation."
    },
    {
      "type": "second",
      "citation": "Rom 9:1-5",
      "summary": "Serving Christ involves some pain."
    },
    {
      "type": "gospel_verse",
      "citation": "See Psalm 130:5",
      "summary": "I wait for the Lord;\nmy soul waits for his word."
    },
    {
      "type": "gospel",
      "citation": "Matthew 14:22-33",
      "summary": "Jesus walks on the water."
    }
  ],
  "antiphons": [
    {
      "type": "entrance",
      "option": 1,
      "citation": "Cf. Ps 74 (73):20, 19, 22, 23",
      "text": "Look to your covenant, O Lord,\nand forget not the life of your poor ones for ever.\nArise, O God, and defend your cause,\nand forget not the cries of those who seek you."
    },
    {
      "type": "communion",
      "option": 1,
      "citation": "Ps 147:12, 14",
      "text": "O Jerusalem, glorify the Lord,\nwho gives you your fill of finest wheat."
    },
    {
      "type": "communion",
      "option": 2,
      "citation": "Roman Missal — Cf. Jn 6:51",
      "text": "The bread that I will give, says the Lord,\nis my flesh for the life of the world."
    }
  ],
  "planningNotes": [],
  "musicPlans": [
    {
      "community": "Reflections",
      "communityId": "reflections",
      "date": "Year A — Aug 08, 2026 (Sat)",
      "presider": "TBD",
      "penitentialAct": {
        "title": "Kyrie • Misa Del Mundo",
        "composer": "Only if needed. Talk to presider!"
      },
      "gloria": {
        "title": "Glory to God (Through-composed Setting)",
        "composer": "Mass of Renewal • Curtis Stephan"
      },
      "gospelAcclamation": {
        "title": "Alleluia (Mass of Joy & Peace)",
        "composer": "Song Title"
      },
      "lordsPrayer": {
        "title": "Chanted Our Father (Snow)",
        "composer": "Jennings/Paregorius"
      },
      "fractionRite": {
        "title": "Lamb of God Setting"
      }
    },
    {
      "community": "Foundations",
      "communityId": "foundations",
      "date": "Year A — Aug 09, 2026 (Sun)",
      "presider": "TBD",
      "penitentialAct": {
        "title": "Kyrie (Gift of God) • Adapted Version",
        "composer": "Marty Haugen • Arranged by David Locwood"
      },
      "gloria": {
        "title": "Glory to God (Mass of Joy & Peace)",
        "composer": "Alonso • Arr. by Houze OR Arr. by Lockwood"
      },
      "eucharisticAcclamations": {
        "massSettingName": "Mass of Glory • Bob Hurd • Arr. by Dan Houze"
      },
      "lordsPrayer": {
        "title": "Chanted Our Father (Snow)",
        "composer": "Jennings • Paregorius"
      },
      "fractionRite": {
        "title": "Lamb of God (Mass of Glory)"
      }
    },
    {
      "community": "Generations",
      "communityId": "generations",
      "date": "Year A — Aug 09, 2026 (Sun)",
      "presider": "TBD",
      "penitentialAct": {
        "title": "Kyrie • Misa Del Mundo",
        "composer": "If needed. Talk to presider!"
      },
      "gloria": {
        "title": "Glory, Glory, Gloria!",
        "composer": "Tony Alonso • Arr. by Dan Houze"
      },
      "gospelAcclamation": {
        "title": "Setting from Mass of ???",
        "composer": "Song Title"
      },
      "eucharisticAcclamations": {
        "massSettingName": "Mass of Restoration",
        "composer": "Joshua Blakesley"
      },
      "lordsPrayer": {
        "title": "(Echo) Our Father",
        "composer": "Jerome Andrews • Arranged by Dan Houze"
      },
      "fractionRite": {
        "title": "Lamb of God (Resoration)"
      }
    },
    {
      "community": "Heritage",
      "communityId": "heritage",
      "date": "Year A — Aug 09, 2026 (Sun)",
      "presider": "TBD",
      "penitentialAct": {
        "title": "Kyrie • Misa Del Mundo",
        "composer": "Only if needed. Talk to presider!"
      },
      "gloria": {
        "title": "Glory to God (Mass of Christ the Savior)",
        "composer": "Dan Schutte"
      },
      "eucharisticAcclamations": {
        "massSettingName": "Mass of Christ the Savior - Dan Schutte"
      },
      "lordsPrayer": {
        "title": "Echo Our Father",
        "composer": "Andrews, Arr. Bonilla • Lockwood • Fajardo"
      },
      "fractionRite": {
        "title": "Lamb of God (Mass of Christ the Savior)"
      }
    },
    {
      "community": "Elevations",
      "communityId": "elevations",
      "date": "Year A — Aug 09, 2026 (Sun)",
      "presider": "TBD",
      "penitentialAct": {
        "title": "Kyrie • Misa Del Mundo",
        "composer": "Only if needed. Talk to presider!"
      },
      "gloria": {
        "title": "Glory, Glory, Gloria!"
      },
      "gospelAcclamation": {
        "title": "Setting from Mass of ???",
        "verse": "Song Title"
      },
      "eucharisticAcclamations": {
        "massSettingName": "Mass of Restoration • Joshua Blakesley"
      },
      "lordsPrayer": {
        "title": "Echo Our Father",
        "composer": "Andrews, Arr. Bonilla • Lockwood • Fajardo"
      },
      "fractionRite": {
        "title": "Lamb of God (Resoration)"
      }
    }
  ],
  "occasionResources": []
}